read_cheque/__init__.py
read_cheque-0.1.dist-info/LICENCE.txt
read_cheque-0.1.dist-info/METADATA
read_cheque-0.1.dist-info/WHEEL
read_cheque-0.1.dist-info/top_level.txt
read_cheque-0.1.dist-info/RECORD
